hepmc3-3.3.1-2.data/data/bin/HepMC3-config
hepmc3-3.3.1-2.data/data/include/HepMC3/AssociatedParticle.h
hepmc3-3.3.1-2.data/data/include/HepMC3/Attribute.h
hepmc3-3.3.1-2.data/data/include/HepMC3/AttributeFeature.h
hepmc3-3.3.1-2.data/data/include/HepMC3/CompressedIO.h
hepmc3-3.3.1-2.data/data/include/HepMC3/Errors.h
hepmc3-3.3.1-2.data/data/include/HepMC3/Feature.h
hepmc3-3.3.1-2.data/data/include/HepMC3/Filter.h
hepmc3-3.3.1-2.data/data/include/HepMC3/FilterAttribute.h
hepmc3-3.3.1-2.data/data/include/HepMC3/FourVector.h
hepmc3-3.3.1-2.data/data/include/HepMC3/GenCrossSection.h
hepmc3-3.3.1-2.data/data/include/HepMC3/GenCrossSection_fwd.h
hepmc3-3.3.1-2.data/data/include/HepMC3/GenEvent.h
hepmc3-3.3.1-2.data/data/include/HepMC3/GenHeavyIon.h
hepmc3-3.3.1-2.data/data/include/HepMC3/GenHeavyIon_fwd.h
hepmc3-3.3.1-2.data/data/include/HepMC3/GenParticle.h
hepmc3-3.3.1-2.data/data/include/HepMC3/GenParticle_fwd.h
hepmc3-3.3.1-2.data/data/include/HepMC3/GenPdfInfo.h
hepmc3-3.3.1-2.data/data/include/HepMC3/GenPdfInfo_fwd.h
hepmc3-3.3.1-2.data/data/include/HepMC3/GenRunInfo.h
hepmc3-3.3.1-2.data/data/include/HepMC3/GenVertex.h
hepmc3-3.3.1-2.data/data/include/HepMC3/GenVertex_fwd.h
hepmc3-3.3.1-2.data/data/include/HepMC3/HEPEVT_Helpers.h
hepmc3-3.3.1-2.data/data/include/HepMC3/HEPEVT_Wrapper.h
hepmc3-3.3.1-2.data/data/include/HepMC3/HEPEVT_Wrapper_Runtime.h
hepmc3-3.3.1-2.data/data/include/HepMC3/HEPEVT_Wrapper_Runtime_Static.h
hepmc3-3.3.1-2.data/data/include/HepMC3/HEPEVT_Wrapper_Template.h
hepmc3-3.3.1-2.data/data/include/HepMC3/HepMC3.h
hepmc3-3.3.1-2.data/data/include/HepMC3/LHEF.h
hepmc3-3.3.1-2.data/data/include/HepMC3/LHEFAttributes.h
hepmc3-3.3.1-2.data/data/include/HepMC3/Print.h
hepmc3-3.3.1-2.data/data/include/HepMC3/PrintStreams.h
hepmc3-3.3.1-2.data/data/include/HepMC3/Reader.h
hepmc3-3.3.1-2.data/data/include/HepMC3/ReaderAscii.h
hepmc3-3.3.1-2.data/data/include/HepMC3/ReaderAsciiHepMC2.h
hepmc3-3.3.1-2.data/data/include/HepMC3/ReaderFactory.h
hepmc3-3.3.1.dist-info/licenses/AUTHORS
hepmc3-3.3.1.dist-info/licenses/COPYING
hepmc3-3.3.1.dist-info/licenses/LICENCE
hepmc3-3.3.1.dist-info/METADATA
hepmc3-3.3.1.dist-info/WHEEL
hepmc3-3.3.1.dist-info/top_level.txt
hepmc3-3.3.1.dist-info/RECORD
