Metadata-Version: 2.1
Name: HepMC3
Version: 3.3.1
Summary: HepMC3 library and Python bindings for HepMC3
Home-page: https://gitlab.cern.ch/hepmc/HepMC3
Author: HepMC3 Developers
Author-email: hepmc-dev@cern.ch
License: GPLv3
Platform: any
Classifier: Programming Language :: Python 
Classifier: Operating System :: OS Independent
License-File: LICENCE
License-File: COPYING
License-File: AUTHORS
